MANIFEST.in
readme.md
setup.cfg
setup.py
kivy_okapi.egg-info/PKG-INFO
kivy_okapi.egg-info/SOURCES.txt
kivy_okapi.egg-info/dependency_links.txt
kivy_okapi.egg-info/not-zip-safe
kivy_okapi.egg-info/pbr.json
kivy_okapi.egg-info/top_level.txt
okapi/__init__.py
okapi/actors.py
okapi/app.py
okapi/base.py
okapi/ground.py
okapi/level.py
okapi/screen.py
okapi/screen_manager.py
okapi/sprite.py
okapi/engine/__init__.py
okapi/engine/actors.py
okapi/engine/base.py
okapi/engine/game.py
okapi/engine/ground.py
okapi/engine/level.py
okapi/engine/level_file_reader.py