Metadata-Version: 1.1
Name: kivy-okapi
Version: 0.1.1
Summary: Grid-based game framework built with Kivy 1.9
Home-page: https://github.com/craiglabenz/kivy-okapi
Author: Craig Labenz
Author-email: craig.labenz@gmail.com
License: MIT
Download-URL: https://github.com/craiglabenz/kivy-okapi/tarball/0.1.1
Keywords: kivy,python,python2,game,games,grid,grid-based
Platform: UNKNOWN
Classifier: Topic :: Games/Entertainment
Classifier: Intended Audience :: Developers
Classifier: Programming Language :: Python
Classifier: Development Status :: 3 - Alpha
Classifier: Natural Language :: English
